licensename/__init__.py
licensename/known_licenses.py
licensename/licensename.py
licensename-0.4.2.dist-info/DESCRIPTION.rst
licensename-0.4.2.dist-info/METADATA
licensename-0.4.2.dist-info/RECORD
licensename-0.4.2.dist-info/WHEEL
licensename-0.4.2.dist-info/entry_points.txt
licensename-0.4.2.dist-info/metadata.json
licensename-0.4.2.dist-info/top_level.txt
